simplify_service_layer_base/service.py
simplify_service_layer_base/service_base.py
simplify_service_layer_base/validation/validator.py
simplify_service_layer_base-0.4.4.dist-info/METADATA
simplify_service_layer_base-0.4.4.dist-info/WHEEL
simplify_service_layer_base-0.4.4.dist-info/RECORD
