Metadata-Version: 2.3
Name: simplify-service-layer-base
Version: 0.4.4
Summary: simplify service layer for python
License: ISC
Author: jongwoo Yoo
Author-email: webdeveloper.kr@gmail.com
Requires-Python: >=3.8,<4.0
Classifier: License :: OSI Approved
Classifier: Programming Language :: Python :: 3
Classifier: Programming Language :: Python :: 3.8
Classifier: Programming Language :: Python :: 3.9
Classifier: Programming Language :: Python :: 3.10
Classifier: Programming Language :: Python :: 3.11
Classifier: Programming Language :: Python :: 3.12
Classifier: Programming Language :: Python :: 3.13
Requires-Dist: jsonschema (>=4.23.0,<5.0.0)
Project-URL: Repository, https://github.com/simplify-service-layer/python
